nnRv.v

`define RAM_SIZE	1024
`define REG_NUM		32
`define REG_SIZE	4

`define MOP_UIMM	0
`define MOP_LOGI	1
`define MOP_MEMY	2
`define MOP_JUMP	3

`define SOP_UIMM_L	0
`define SOP_UIMM_H	1

`define SOP_LOGI_ADD	0
`define SOP_LOGI_SUB	1
`define SOP_LOGI_LLS	2
`define SOP_LOGI_LRS	3
`define SOP_LOGI_ARS	4
`define SOP_LOGI_AND	5
`define SOP_LOGI_OR	6
`define SOP_LOGI_XOR	7

`define SOP_MEMY_L	0
`define SOP_MEMY_S	1

`define SOP_JUMP_EQ	0
`define SOP_JUMP_NE	1
`define SOP_JUMP_LT	2
`define SOP_JUMP_GE	3

module nnRvSoc
(
	input		RST_N,
	input		CLK,
	input	[1:0]	KEY,
	output	[3:0]	LED
);
	reg [31:0] RAM [0:`RAM_SIZE-1];
	reg [31:0] REG [0:`REG_NUM-1];

	integer i;
	initial
	begin
		for (i = 0; i < `RAM_SIZE; i++)
		begin
			RAM[i] = 32'd0;
		end
		$readmemh("ram.mem", RAM);
	end

	initial
        begin
                for (i = 0; i < `REG_NUM; i++)
                begin
                        REG[i] = 32'd0;
                end
        end

	reg  [31:0] pc		= 0;
	wire [31:0] instr	= RAM[pc[31:2]];

	wire [7:0]  instr_oper	= instr[31:24];
	wire [4:0]  instr_rd	= instr[23:19];
	wire [4:0]  instr_rs1	= instr[18:14];
	wire [4:0]  instr_rs2	= instr[13:9];
	wire [15:0] instr_uimm	= instr[15:0];

	wire [2:0]  oper_mop	= instr_oper[7:5];
	wire [4:0]  oper_sop	= instr_oper[4:0];

	wire memory_stall = 0;
	wire jump_stall = (oper_mop == `MOP_JUMP) && (
				((oper_sop == `SOP_JUMP_EQ) && (REG[instr_rs1] == REG[instr_rs2])) ||
				((oper_sop == `SOP_JUMP_NE) && (REG[instr_rs1] != REG[instr_rs2])) ||
				((oper_sop == `SOP_JUMP_LT) && (REG[instr_rs1] <  REG[instr_rs2])) ||
				((oper_sop == `SOP_JUMP_GE) && (REG[instr_rs1] >= REG[instr_rs2]))
				);
	wire stall = jump_stall | memory_stall;

	always@(posedge CLK)
	begin
		if (RST_N)
		begin
			if (oper_mop == `MOP_UIMM)
			begin
				case (oper_sop)
					`SOP_UIMM_L	: REG[instr_rd][15:0]  <= instr_uimm;
					`SOP_UIMM_H	: REG[instr_rd][31:16] <= instr_uimm;
				endcase

			end

			if (oper_mop == `MOP_LOGI)
			begin
				case (oper_sop)
					`SOP_LOGI_ADD	: REG[instr_rd] <= REG[instr_rs1] +   REG[instr_rs2];
					`SOP_LOGI_SUB	: REG[instr_rd] <= REG[instr_rs1] -   REG[instr_rs2];
					`SOP_LOGI_LLS	: REG[instr_rd] <= REG[instr_rs1] <<  REG[instr_rs2];
					`SOP_LOGI_LRS	: REG[instr_rd] <= REG[instr_rs1] >>  REG[instr_rs2];
					`SOP_LOGI_ARS	: REG[instr_rd] <= REG[instr_rs1] >>> REG[instr_rs2];
					`SOP_LOGI_AND	: REG[instr_rd] <= REG[instr_rs1] & REG[instr_rs2];
					`SOP_LOGI_OR	: REG[instr_rd] <= REG[instr_rs1] | REG[instr_rs2];
					`SOP_LOGI_XOR	: REG[instr_rd] <= REG[instr_rs1] ^ REG[instr_rs2];
				endcase
			end

			if (oper_mop == `MOP_JUMP)
			begin
				case (oper_sop)
					`SOP_JUMP_EQ	: if (REG[instr_rs1] == REG[instr_rs2]) 
								REG[31] <= REG[instr_rd];
					`SOP_JUMP_NE	: if (REG[instr_rs1] != REG[instr_rs2]) 
								REG[31] <= REG[instr_rd];
					`SOP_JUMP_LT	: if (REG[instr_rs1] <  REG[instr_rs2]) 
								REG[31] <= REG[instr_rd];
					`SOP_JUMP_GE	: if (REG[instr_rs1] >= REG[instr_rs2]) 
								REG[31] <= REG[instr_rd];
				endcase
			end

			if (oper_mop == `MOP_MEMY)
			begin
				case (oper_sop)
					`SOP_MEMY_L	: REG[instr_rd] <= RAM[REG[instr_rs1][31:2] + REG[instr_rs2][31:2]];
					`SOP_MEMY_S	: RAM[REG[instr_rs1][31:2] + REG[instr_rs2][31:2]] <= REG[instr_rd];
				endcase
			end
		end
	end

	always@(negedge CLK)
	begin
		if (RST_N)
		begin
			if (stall)
			begin
				pc <= REG[31];
			end
			else
			begin
				pc <= REG[31] + 4;
				REG[31] <= REG[31] + 4;
			end
		end
	end

endmodule

test.v

`timescale 1ns / 1ps

module test
(
);

	reg CLK	  = 0;
	reg RST_N = 0;

	initial
	begin
		$display("---reset---");
		#(50000) RST_N = 1;
	end

	integer i;
	initial
	begin
		$dumpfile("test.vcd");
		$dumpvars;
		for (i = 0; i < 10; i++)
			$dumpvars(0, nnRvSoc.RAM[i]);
		for (i = 0; i < 32; i++)
			$dumpvars(0, nnRvSoc.REG[i]);

		for (i = 0; i < 1000; i++)
			#(1000000) CLK = !CLK;
	end

	wire [3:0] LED;
	wire [1:0] KEY;

	nnRvSoc nnRvSoc(RST_N, CLK, KEY, LED);

endmodule

test.vcd
$date
	Thu Mar  5 11:40:47 2020
$end
$version
	Icarus Verilog
$end
$timescale
	1ps
$end
$scope module test $end
$var wire 2 ! KEY [1:0] $end
$var wire 4 " LED [3:0] $end
$var reg 1 # CLK $end
$var reg 1 $ RST_N $end
$var integer 32 % i [31:0] $end
$scope module nnRvSoc $end
$var wire 1 # CLK $end
$var wire 2 & KEY [1:0] $end
$var wire 4 ' LED [3:0] $end
$var wire 1 $ RST_N $end
$var wire 32 ( instr [31:0] $end
$var wire 1 ) jump_stall $end
$var wire 1 * memory_stall $end
$var wire 1 + stall $end
$var wire 5 , oper_sop [4:0] $end
$var wire 3 - oper_mop [2:0] $end
$var wire 16 . instr_uimm [15:0] $end
$var wire 5 / instr_rs2 [4:0] $end
$var wire 5 0 instr_rs1 [4:0] $end
$var wire 5 1 instr_rd [4:0] $end
$var wire 8 2 instr_oper [7:0] $end
$var reg 32 3 pc [31:0] $end
$var integer 32 4 i [31:0] $end
$upscope $end
$upscope $end
$scope module test $end
$scope module nnRvSoc $end
$var reg 32 5 \RAM[0] [31:0] $end
$upscope $end
$upscope $end
$scope module test $end
$scope module nnRvSoc $end
$var reg 32 6 \RAM[1] [31:0] $end
$upscope $end
$upscope $end
$scope module test $end
$scope module nnRvSoc $end
$var reg 32 7 \RAM[2] [31:0] $end
$upscope $end
$upscope $end
$scope module test $end
$scope module nnRvSoc $end
$var reg 32 8 \RAM[3] [31:0] $end
$upscope $end
$upscope $end
$scope module test $end
$scope module nnRvSoc $end
$var reg 32 9 \RAM[4] [31:0] $end
$upscope $end
$upscope $end
$scope module test $end
$scope module nnRvSoc $end
$var reg 32 : \RAM[5] [31:0] $end
$upscope $end
$upscope $end
$scope module test $end
$scope module nnRvSoc $end
$var reg 32 ; \RAM[6] [31:0] $end
$upscope $end
$upscope $end
$scope module test $end
$scope module nnRvSoc $end
$var reg 32 < \RAM[7] [31:0] $end
$upscope $end
$upscope $end
$scope module test $end
$scope module nnRvSoc $end
$var reg 32 = \RAM[8] [31:0] $end
$upscope $end
$upscope $end
$scope module test $end
$scope module nnRvSoc $end
$var reg 32 > \RAM[9] [31:0] $end
$upscope $end
$upscope $end
$scope module test $end
$scope module nnRvSoc $end
$var reg 32 ? \REG[0] [31:0] $end
$upscope $end
$upscope $end
$scope module test $end
$scope module nnRvSoc $end
$var reg 32 @ \REG[1] [31:0] $end
$upscope $end
$upscope $end
$scope module test $end
$scope module nnRvSoc $end
$var reg 32 A \REG[2] [31:0] $end
$upscope $end
$upscope $end
$scope module test $end
$scope module nnRvSoc $end
$var reg 32 B \REG[3] [31:0] $end
$upscope $end
$upscope $end
$scope module test $end
$scope module nnRvSoc $end
$var reg 32 C \REG[4] [31:0] $end
$upscope $end
$upscope $end
$scope module test $end
$scope module nnRvSoc $end
$var reg 32 D \REG[5] [31:0] $end
$upscope $end
$upscope $end
$scope module test $end
$scope module nnRvSoc $end
$var reg 32 E \REG[6] [31:0] $end
$upscope $end
$upscope $end
$scope module test $end
$scope module nnRvSoc $end
$var reg 32 F \REG[7] [31:0] $end
$upscope $end
$upscope $end
$scope module test $end
$scope module nnRvSoc $end
$var reg 32 G \REG[8] [31:0] $end
$upscope $end
$upscope $end
$scope module test $end
$scope module nnRvSoc $end
$var reg 32 H \REG[9] [31:0] $end
$upscope $end
$upscope $end
$scope module test $end
$scope module nnRvSoc $end
$var reg 32 I \REG[10] [31:0] $end
$upscope $end
$upscope $end
$scope module test $end
$scope module nnRvSoc $end
$var reg 32 J \REG[11] [31:0] $end
$upscope $end
$upscope $end
$scope module test $end
$scope module nnRvSoc $end
$var reg 32 K \REG[12] [31:0] $end
$upscope $end
$upscope $end
$scope module test $end
$scope module nnRvSoc $end
$var reg 32 L \REG[13] [31:0] $end
$upscope $end
$upscope $end
$scope module test $end
$scope module nnRvSoc $end
$var reg 32 M \REG[14] [31:0] $end
$upscope $end
$upscope $end
$scope module test $end
$scope module nnRvSoc $end
$var reg 32 N \REG[15] [31:0] $end
$upscope $end
$upscope $end
$scope module test $end
$scope module nnRvSoc $end
$var reg 32 O \REG[16] [31:0] $end
$upscope $end
$upscope $end
$scope module test $end
$scope module nnRvSoc $end
$var reg 32 P \REG[17] [31:0] $end
$upscope $end
$upscope $end
$scope module test $end
$scope module nnRvSoc $end
$var reg 32 Q \REG[18] [31:0] $end
$upscope $end
$upscope $end
$scope module test $end
$scope module nnRvSoc $end
$var reg 32 R \REG[19] [31:0] $end
$upscope $end
$upscope $end
$scope module test $end
$scope module nnRvSoc $end
$var reg 32 S \REG[20] [31:0] $end
$upscope $end
$upscope $end
$scope module test $end
$scope module nnRvSoc $end
$var reg 32 T \REG[21] [31:0] $end
$upscope $end
$upscope $end
$scope module test $end
$scope module nnRvSoc $end
$var reg 32 U \REG[22] [31:0] $end
$upscope $end
$upscope $end
$scope module test $end
$scope module nnRvSoc $end
$var reg 32 V \REG[23] [31:0] $end
$upscope $end
$upscope $end
$scope module test $end
$scope module nnRvSoc $end
$var reg 32 W \REG[24] [31:0] $end
$upscope $end
$upscope $end
$scope module test $end
$scope module nnRvSoc $end
$var reg 32 X \REG[25] [31:0] $end
$upscope $end
$upscope $end
$scope module test $end
$scope module nnRvSoc $end
$var reg 32 Y \REG[26] [31:0] $end
$upscope $end
$upscope $end
$scope module test $end
$scope module nnRvSoc $end
$var reg 32 Z \REG[27] [31:0] $end
$upscope $end
$upscope $end
$scope module test $end
$scope module nnRvSoc $end
$var reg 32 [ \REG[28] [31:0] $end
$upscope $end
$upscope $end
$scope module test $end
$scope module nnRvSoc $end
$var reg 32 \ \REG[29] [31:0] $end
$upscope $end
$upscope $end
$scope module test $end
$scope module nnRvSoc $end
$var reg 32 ] \REG[30] [31:0] $end
$upscope $end
$upscope $end
$scope module test $end
$scope module nnRvSoc $end
$var reg 32 ^ \REG[31] [31:0] $end
$upscope $end
$upscope $end
$enddefinitions $end
#0
$dumpvars
b0 ^
b0 ]
b0 \
b0 [
b0 Z
b0 Y
b0 X
b0 W
b0 V
b0 U
b0 T
b0 S
b0 R
b0 Q
b0 P
b0 O
b0 N
b0 M
b0 L
b0 K
b0 J
b0 I
b0 H
b0 G
b0 F
b0 E
b0 D
b0 C
b0 B
b0 A
b0 @
b0 ?
b1010000000000000011000 >
b1000001001110001100000000000000 =
b100000001110011100100000000000 <
b1000000001110001100000000000000 ;
b1000000000000000000001 :
b1000110000000000000000000 9
b110000000000000110000 8
b100000000110000000000000000000 7
b100000000100000000000000000000 6
b100000000010000000000000000000 5
b100000 4
b0 3
b100000 2
b1 1
b0 0
b0 /
b0 .
b1 -
b0 ,
0+
0*
0)
b100000000010000000000000000000 (
bz '
bz &
b0 %
0$
0#
bz "
bz !
$end
#50000000
1$
#1000000000
b0 @
b1 %
1#
#2000000000
b10 1
b100000000100000000000000000000 (
b100 ^
b100 3
b10 %
0#
#3000000000
b0 A
b11 %
1#
#4000000000
b11 1
b100000000110000000000000000000 (
b1000 ^
b1000 3
b100 %
0#
#5000000000
b0 B
b101 %
1#
#6000000000
b0 -
b0 2
b110000 .
b110000000000000110000 (
b1100 ^
b1100 3
b110 %
0#
#7000000000
b110000 B
b111 %
1#
#8000000000
b1 ,
b1 2
b0 .
b1000110000000000000000000 (
b10000 ^
b10000 3
b1000 %
0#
#9000000000
b110000 B
b1001 %
1#
#10000000000
b0 ,
b0 2
b100 1
b1 .
b1000000000000000000001 (
b10100 ^
b10100 3
b1010 %
0#
#11000000000
b1 C
b1011 %
1#
#12000000000
b10 -
b1000000 2
b111 1
b11 0
b1100000000000000 .
b1000000001110001100000000000000 (
b11000 ^
b11000 3
b1100 %
0#
#13000000000
b100000000010000000000000000000 F
b1101 %
1#
#14000000000
b1 -
b100000 2
b111 0
b100 /
b1100100000000000 .
b100000001110011100100000000000 (
b11100 ^
b11100 3
b1110 %
0#
#15000000000
b100000000010000000000000000001 F
b1111 %
1#
#16000000000
b10 -
b1 ,
b1000001 2
b11 0
b0 /
b1100000000000000 .
b1000001001110001100000000000000 (
b100000 ^
b100000 3
b10000 %
0#
#17000000000
b10001 %
1#
#18000000000
b0 -
b0 ,
b0 2
b101 1
b0 0
b11000 .
b1010000000000000011000 (
b100100 ^
b100100 3
b10010 %
0#
#19000000000
b11000 D
b10011 %
1#
#20000000000
b1 ,
b1 2
b0 .
b1001010000000000000000000 (
b101000 ^
b101000 3
b10100 %
0#
#21000000000
b11000 D
b10101 %
1#
#22000000000
1+
1)
b11 -
b1100001 2
b11111 0
b1100000000000000 .
b1100001001011111100000000000000 (
b101100 ^
b101100 3
b10110 %
0#
#23000000000
b11000 ^
b10111 %
1#
#24000000000
0+
0)
b10 -
b0 ,
b1000000 2
b111 1
b11 0
b1000000001110001100000000000000 (
b11000 3
b11000 %
0#
#25000000000
b100000000010000000000000000001 F
b11001 %
1#
#26000000000
b1 -
b100000 2
b111 0
b100 /
b1100100000000000 .
b100000001110011100100000000000 (
b11100 ^
b11100 3
b11010 %
0#
#27000000000
b100000000010000000000000000010 F
b11011 %
1#
#28000000000
b10 -
b1 ,
b1000001 2
b11 0
b0 /
b1100000000000000 .
b1000001001110001100000000000000 (
b100000 ^
b100000 3
b11100 %
0#
#29000000000
b11101 %
1#
#30000000000
b0 -
b0 ,
b0 2
b101 1
b0 0
b11000 .
b1010000000000000011000 (
b100100 ^
b100100 3
b11110 %
0#
#31000000000
b11000 D
b11111 %
1#
#32000000000
b1 ,
b1 2
b0 .
b1001010000000000000000000 (
b101000 ^
b101000 3
b100000 %
0#
#33000000000
b11000 D
b100001 %
1#
#34000000000
1+
1)
b11 -
b1100001 2
b11111 0
b1100000000000000 .
b1100001001011111100000000000000 (
b101100 ^
b101100 3
b100010 %
0#
#35000000000
b11000 ^
b100011 %
1#
#36000000000
0+
0)
b10 -
b0 ,
b1000000 2
b111 1
b11 0
b1000000001110001100000000000000 (
b11000 3
b100100 %
0#
#37000000000
b100000000010000000000000000010 F
b100101 %
1#
#38000000000
b1 -
b100000 2
b111 0
b100 /
b1100100000000000 .
b100000001110011100100000000000 (
b11100 ^
b11100 3
b100110 %
0#
#39000000000
b100000000010000000000000000011 F
b100111 %
1#
#40000000000
b10 -
b1 ,
b1000001 2
b11 0
b0 /
b1100000000000000 .
b1000001001110001100000000000000 (
b100000 ^
b100000 3
b101000 %
0#
#41000000000
b101001 %
1#
#42000000000
b0 -
b0 ,
b0 2
b101 1
b0 0
b11000 .
b1010000000000000011000 (
b100100 ^
b100100 3
b101010 %
0#
#43000000000
b11000 D
b101011 %
1#
#44000000000
b1 ,
b1 2
b0 .
b1001010000000000000000000 (
b101000 ^
b101000 3
b101100 %
0#
#45000000000
b11000 D
b101101 %
1#
#46000000000
1+
1)
b11 -
b1100001 2
b11111 0
b1100000000000000 .
b1100001001011111100000000000000 (
b101100 ^
b101100 3
b101110 %
0#
#47000000000
b11000 ^
b101111 %
1#
#48000000000
0+
0)
b10 -
b0 ,
b1000000 2
b111 1
b11 0
b1000000001110001100000000000000 (
b11000 3
b110000 %
0#
#49000000000
b100000000010000000000000000011 F
b110001 %
1#
#50000000000
b1 -
b100000 2
b111 0
b100 /
b1100100000000000 .
b100000001110011100100000000000 (
b11100 ^
b11100 3
b110010 %
0#
#51000000000
b100000000010000000000000000100 F
b110011 %
1#
#52000000000
b10 -
b1 ,
b1000001 2
b11 0
b0 /
b1100000000000000 .
b1000001001110001100000000000000 (
b100000 ^
b100000 3
b110100 %
0#
#53000000000
b110101 %
1#
#54000000000
b0 -
b0 ,
b0 2
b101 1
b0 0
b11000 .
b1010000000000000011000 (
b100100 ^
b100100 3
b110110 %
0#
#55000000000
b11000 D
b110111 %
1#
#56000000000
b1 ,
b1 2
b0 .
b1001010000000000000000000 (
b101000 ^
b101000 3
b111000 %
0#
#57000000000
b11000 D
b111001 %
1#
#58000000000
1+
1)
b11 -
b1100001 2
b11111 0
b1100000000000000 .
b1100001001011111100000000000000 (
b101100 ^
b101100 3
b111010 %
0#
#59000000000
b11000 ^
b111011 %
1#
#60000000000
0+
0)
b10 -
b0 ,
b1000000 2
b111 1
b11 0
b1000000001110001100000000000000 (
b11000 3
b111100 %
0#
#61000000000
b100000000010000000000000000100 F
b111101 %
1#
#62000000000
b1 -
b100000 2
b111 0
b100 /
b1100100000000000 .
b100000001110011100100000000000 (
b11100 ^
b11100 3
b111110 %
0#
#63000000000
b100000000010000000000000000101 F
b111111 %
1#
#64000000000
b10 -
b1 ,
b1000001 2
b11 0
b0 /
b1100000000000000 .
b1000001001110001100000000000000 (
b100000 ^
b100000 3
b1000000 %
0#
#65000000000
b1000001 %
1#
#66000000000
b0 -
b0 ,
b0 2
b101 1
b0 0
b11000 .
b1010000000000000011000 (
b100100 ^
b100100 3
b1000010 %
0#
#67000000000
b11000 D
b1000011 %
1#
#68000000000
b1 ,
b1 2
b0 .
b1001010000000000000000000 (
b101000 ^
b101000 3
b1000100 %
0#
#69000000000
b11000 D
b1000101 %
1#
#70000000000
1+
1)
b11 -
b1100001 2
b11111 0
b1100000000000000 .
b1100001001011111100000000000000 (
b101100 ^
b101100 3
b1000110 %
0#
#71000000000
b11000 ^
b1000111 %
1#
#72000000000
0+
0)
b10 -
b0 ,
b1000000 2
b111 1
b11 0
b1000000001110001100000000000000 (
b11000 3
b1001000 %
0#
#73000000000
b100000000010000000000000000101 F
b1001001 %
1#
#74000000000
b1 -
b100000 2
b111 0
b100 /
b1100100000000000 .
b100000001110011100100000000000 (
b11100 ^
b11100 3
b1001010 %
0#
#75000000000
b100000000010000000000000000110 F
b1001011 %
1#
#76000000000
b10 -
b1 ,
b1000001 2
b11 0
b0 /
b1100000000000000 .
b1000001001110001100000000000000 (
b100000 ^
b100000 3
b1001100 %
0#
#77000000000
b1001101 %
1#
#78000000000
b0 -
b0 ,
b0 2
b101 1
b0 0
b11000 .
b1010000000000000011000 (
b100100 ^
b100100 3
b1001110 %
0#
#79000000000
b11000 D
b1001111 %
1#
#80000000000
b1 ,
b1 2
b0 .
b1001010000000000000000000 (
b101000 ^
b101000 3
b1010000 %
0#
#81000000000
b11000 D
b1010001 %
1#
#82000000000
1+
1)
b11 -
b1100001 2
b11111 0
b1100000000000000 .
b1100001001011111100000000000000 (
b101100 ^
b101100 3
b1010010 %
0#
#83000000000
b11000 ^
b1010011 %
1#
#84000000000
0+
0)
b10 -
b0 ,
b1000000 2
b111 1
b11 0
b1000000001110001100000000000000 (
b11000 3
b1010100 %
0#
#85000000000
b100000000010000000000000000110 F
b1010101 %
1#
#86000000000
b1 -
b100000 2
b111 0
b100 /
b1100100000000000 .
b100000001110011100100000000000 (
b11100 ^
b11100 3
b1010110 %
0#
#87000000000
b100000000010000000000000000111 F
b1010111 %
1#
#88000000000
b10 -
b1 ,
b1000001 2
b11 0
b0 /
b1100000000000000 .
b1000001001110001100000000000000 (
b100000 ^
b100000 3
b1011000 %
0#
#89000000000
b1011001 %
1#
#90000000000
b0 -
b0 ,
b0 2
b101 1
b0 0
b11000 .
b1010000000000000011000 (
b100100 ^
b100100 3
b1011010 %
0#
#91000000000
b11000 D
b1011011 %
1#
#92000000000
b1 ,
b1 2
b0 .
b1001010000000000000000000 (
b101000 ^
b101000 3
b1011100 %
0#
#93000000000
b11000 D
b1011101 %
1#
#94000000000
1+
1)
b11 -
b1100001 2
b11111 0
b1100000000000000 .
b1100001001011111100000000000000 (
b101100 ^
b101100 3
b1011110 %
0#
#95000000000
b11000 ^
b1011111 %
1#
#96000000000
0+
0)
b10 -
b0 ,
b1000000 2
b111 1
b11 0
b1000000001110001100000000000000 (
b11000 3
b1100000 %
0#
#97000000000
b100000000010000000000000000111 F
b1100001 %
1#
#98000000000
b1 -
b100000 2
b111 0
b100 /
b1100100000000000 .
b100000001110011100100000000000 (
b11100 ^
b11100 3
b1100010 %
0#
#99000000000
b100000000010000000000000001000 F
b1100011 %
1#
#100000000000
b10 -
b1 ,
b1000001 2
b11 0
b0 /
b1100000000000000 .
b1000001001110001100000000000000 (
b100000 ^
b100000 3
b1100100 %
0#
#101000000000
b1100101 %
1#
#102000000000
b0 -
b0 ,
b0 2
b101 1
b0 0
b11000 .
b1010000000000000011000 (
b100100 ^
b100100 3
b1100110 %
0#
#103000000000
b11000 D
b1100111 %
1#
#104000000000
b1 ,
b1 2
b0 .
b1001010000000000000000000 (
b101000 ^
b101000 3
b1101000 %
0#
#105000000000
b11000 D
b1101001 %
1#
#106000000000
1+
1)
b11 -
b1100001 2
b11111 0
b1100000000000000 .
b1100001001011111100000000000000 (
b101100 ^
b101100 3
b1101010 %
0#
#107000000000
b11000 ^
b1101011 %
1#
#108000000000
0+
0)
b10 -
b0 ,
b1000000 2
b111 1
b11 0
b1000000001110001100000000000000 (
b11000 3
b1101100 %
0#
#109000000000
b100000000010000000000000001000 F
b1101101 %
1#
#110000000000
b1 -
b100000 2
b111 0
b100 /
b1100100000000000 .
b100000001110011100100000000000 (
b11100 ^
b11100 3
b1101110 %
0#
#111000000000
b100000000010000000000000001001 F
b1101111 %
1#
#112000000000
b10 -
b1 ,
b1000001 2
b11 0
b0 /
b1100000000000000 .
b1000001001110001100000000000000 (
b100000 ^
b100000 3
b1110000 %
0#
#113000000000
b1110001 %
1#
#114000000000
b0 -
b0 ,
b0 2
b101 1
b0 0
b11000 .
b1010000000000000011000 (
b100100 ^
b100100 3
b1110010 %
0#
#115000000000
b11000 D
b1110011 %
1#
#116000000000
b1 ,
b1 2
b0 .
b1001010000000000000000000 (
b101000 ^
b101000 3
b1110100 %
0#
#117000000000
b11000 D
b1110101 %
1#
#118000000000
1+
1)
b11 -
b1100001 2
b11111 0
b1100000000000000 .
b1100001001011111100000000000000 (
b101100 ^
b101100 3
b1110110 %
0#
#119000000000
b11000 ^
b1110111 %
1#
#120000000000
0+
0)
b10 -
b0 ,
b1000000 2
b111 1
b11 0
b1000000001110001100000000000000 (
b11000 3
b1111000 %
0#
#121000000000
b100000000010000000000000001001 F
b1111001 %
1#
#122000000000
b1 -
b100000 2
b111 0
b100 /
b1100100000000000 .
b100000001110011100100000000000 (
b11100 ^
b11100 3
b1111010 %
0#
#123000000000
b100000000010000000000000001010 F
b1111011 %
1#
#124000000000
b10 -
b1 ,
b1000001 2
b11 0
b0 /
b1100000000000000 .
b1000001001110001100000000000000 (
b100000 ^
b100000 3
b1111100 %
0#
#125000000000
b1111101 %
1#
#126000000000
b0 -
b0 ,
b0 2
b101 1
b0 0
b11000 .
b1010000000000000011000 (
b100100 ^
b100100 3
b1111110 %
0#
#127000000000
b11000 D
b1111111 %
1#
#128000000000
b1 ,
b1 2
b0 .
b1001010000000000000000000 (
b101000 ^
b101000 3
b10000000 %
0#
#129000000000
b11000 D
b10000001 %
1#
#130000000000
1+
1)
b11 -
b1100001 2
b11111 0
b1100000000000000 .
b1100001001011111100000000000000 (
b101100 ^
b101100 3
b10000010 %
0#
#131000000000
b11000 ^
b10000011 %
1#
#132000000000
0+
0)
b10 -
b0 ,
b1000000 2
b111 1
b11 0
b1000000001110001100000000000000 (
b11000 3
b10000100 %
0#
#133000000000
b100000000010000000000000001010 F
b10000101 %
1#
#134000000000
b1 -
b100000 2
b111 0
b100 /
b1100100000000000 .
b100000001110011100100000000000 (
b11100 ^
b11100 3
b10000110 %
0#
#135000000000
b100000000010000000000000001011 F
b10000111 %
1#
#136000000000
b10 -
b1 ,
b1000001 2
b11 0
b0 /
b1100000000000000 .
b1000001001110001100000000000000 (
b100000 ^
b100000 3
b10001000 %
0#
#137000000000
b10001001 %
1#
#138000000000
b0 -
b0 ,
b0 2
b101 1
b0 0
b11000 .
b1010000000000000011000 (
b100100 ^
b100100 3
b10001010 %
0#
#139000000000
b11000 D
b10001011 %
1#
#140000000000
b1 ,
b1 2
b0 .
b1001010000000000000000000 (
b101000 ^
b101000 3
b10001100 %
0#
#141000000000
b11000 D
b10001101 %
1#
#142000000000
1+
1)
b11 -
b1100001 2
b11111 0
b1100000000000000 .
b1100001001011111100000000000000 (
b101100 ^
b101100 3
b10001110 %
0#
#143000000000
b11000 ^
b10001111 %
1#
#144000000000
0+
0)
b10 -
b0 ,
b1000000 2
b111 1
b11 0
b1000000001110001100000000000000 (
b11000 3
b10010000 %
0#
#145000000000
b100000000010000000000000001011 F
b10010001 %
1#
#146000000000
b1 -
b100000 2
b111 0
b100 /
b1100100000000000 .
b100000001110011100100000000000 (
b11100 ^
b11100 3
b10010010 %
0#
#147000000000
b100000000010000000000000001100 F
b10010011 %
1#
#148000000000
b10 -
b1 ,
b1000001 2
b11 0
b0 /
b1100000000000000 .
b1000001001110001100000000000000 (
b100000 ^
b100000 3
b10010100 %
0#
#149000000000
b10010101 %
1#
#150000000000
b0 -
b0 ,
b0 2
b101 1
b0 0
b11000 .
b1010000000000000011000 (
b100100 ^
b100100 3
b10010110 %
0#
#151000000000
b11000 D
b10010111 %
1#
#152000000000
b1 ,
b1 2
b0 .
b1001010000000000000000000 (
b101000 ^
b101000 3
b10011000 %
0#
#153000000000
b11000 D
b10011001 %
1#
#154000000000
1+
1)
b11 -
b1100001 2
b11111 0
b1100000000000000 .
b1100001001011111100000000000000 (
b101100 ^
b101100 3
b10011010 %
0#
#155000000000
b11000 ^
b10011011 %
1#
#156000000000
0+
0)
b10 -
b0 ,
b1000000 2
b111 1
b11 0
b1000000001110001100000000000000 (
b11000 3
b10011100 %
0#
#157000000000
b100000000010000000000000001100 F
b10011101 %
1#
#158000000000
b1 -
b100000 2
b111 0
b100 /
b1100100000000000 .
b100000001110011100100000000000 (
b11100 ^
b11100 3
b10011110 %
0#
#159000000000
b100000000010000000000000001101 F
b10011111 %
1#
#160000000000
b10 -
b1 ,
b1000001 2
b11 0
b0 /
b1100000000000000 .
b1000001001110001100000000000000 (
b100000 ^
b100000 3
b10100000 %
0#
#161000000000
b10100001 %
1#
#162000000000
b0 -
b0 ,
b0 2
b101 1
b0 0
b11000 .
b1010000000000000011000 (
b100100 ^
b100100 3
b10100010 %
0#
#163000000000
b11000 D
b10100011 %
1#
#164000000000
b1 ,
b1 2
b0 .
b1001010000000000000000000 (
b101000 ^
b101000 3
b10100100 %
0#
#165000000000
b11000 D
b10100101 %
1#
#166000000000
1+
1)
b11 -
b1100001 2
b11111 0
b1100000000000000 .
b1100001001011111100000000000000 (
b101100 ^
b101100 3
b10100110 %
0#
#167000000000
b11000 ^
b10100111 %
1#
#168000000000
0+
0)
b10 -
b0 ,
b1000000 2
b111 1
b11 0
b1000000001110001100000000000000 (
b11000 3
b10101000 %
0#
#169000000000
b100000000010000000000000001101 F
b10101001 %
1#
#170000000000
b1 -
b100000 2
b111 0
b100 /
b1100100000000000 .
b100000001110011100100000000000 (
b11100 ^
b11100 3
b10101010 %
0#
#171000000000
b100000000010000000000000001110 F
b10101011 %
1#
#172000000000
b10 -
b1 ,
b1000001 2
b11 0
b0 /
b1100000000000000 .
b1000001001110001100000000000000 (
b100000 ^
b100000 3
b10101100 %
0#
#173000000000
b10101101 %
1#
#174000000000
b0 -
b0 ,
b0 2
b101 1
b0 0
b11000 .
b1010000000000000011000 (
b100100 ^
b100100 3
b10101110 %
0#
#175000000000
b11000 D
b10101111 %
1#
#176000000000
b1 ,
b1 2
b0 .
b1001010000000000000000000 (
b101000 ^
b101000 3
b10110000 %
0#
#177000000000
b11000 D
b10110001 %
1#
#178000000000
1+
1)
b11 -
b1100001 2
b11111 0
b1100000000000000 .
b1100001001011111100000000000000 (
b101100 ^
b101100 3
b10110010 %
0#
#179000000000
b11000 ^
b10110011 %
1#
#180000000000
0+
0)
b10 -
b0 ,
b1000000 2
b111 1
b11 0
b1000000001110001100000000000000 (
b11000 3
b10110100 %
0#
#181000000000
b100000000010000000000000001110 F
b10110101 %
1#
#182000000000
b1 -
b100000 2
b111 0
b100 /
b1100100000000000 .
b100000001110011100100000000000 (
b11100 ^
b11100 3
b10110110 %
0#
#183000000000
b100000000010000000000000001111 F
b10110111 %
1#
#184000000000
b10 -
b1 ,
b1000001 2
b11 0
b0 /
b1100000000000000 .
b1000001001110001100000000000000 (
b100000 ^
b100000 3
b10111000 %
0#
#185000000000
b10111001 %
1#
#186000000000
b0 -
b0 ,
b0 2
b101 1
b0 0
b11000 .
b1010000000000000011000 (
b100100 ^
b100100 3
b10111010 %
0#
#187000000000
b11000 D
b10111011 %
1#
#188000000000
b1 ,
b1 2
b0 .
b1001010000000000000000000 (
b101000 ^
b101000 3
b10111100 %
0#
#189000000000
b11000 D
b10111101 %
1#
#190000000000
1+
1)
b11 -
b1100001 2
b11111 0
b1100000000000000 .
b1100001001011111100000000000000 (
b101100 ^
b101100 3
b10111110 %
0#
#191000000000
b11000 ^
b10111111 %
1#
